{
	"inputs" : 
	[
		{
			"path" : "CMakeLists.txt"
		},
		{
			"isGenerated" : true,
			"path" : "/home/user/YPrC++/TransportCatalogue3/build-debug/CMakeFiles/3.22.2/CMakeSystem.cmake"
		},
		{
			"isCMake" : true,
			"isExternal" : true,
			"path" : "/usr/local/share/cmake-3.22/Modules/CMakeSystemSpecificInitialize.cmake"
		},
		{
			"isGenerated" : true,
			"path" : "/home/user/YPrC++/TransportCatalogue3/build-debug/CMakeFiles/3.22.2/CMakeCXXCompiler.cmake"
		},
		{
			"isCMake" : true,
			"isExternal" : true,
			"path" : "/usr/local/share/cmake-3.22/Modules/CMakeSystemSpecificInformation.cmake"
		},
		{
			"isCMake" : true,
			"isExternal" : true,
			"path" : "/usr/local/share/cmake-3.22/Modules/CMakeGenericSystem.cmake"
		},
		{
			"isCMake" : true,
			"isExternal" : true,
			"path" : "/usr/local/share/cmake-3.22/Modules/CMakeInitializeConfigs.cmake"
		},
		{
			"isCMake" : true,
			"isExternal" : true,
			"path" : "/usr/local/share/cmake-3.22/Modules/Platform/Linux.cmake"
		},
		{
			"isCMake" : true,
			"isExternal" : true,
			"path" : "/usr/local/share/cmake-3.22/Modules/Platform/UnixPaths.cmake"
		},
		{
			"isCMake" : true,
			"isExternal" : true,
			"path" : "/usr/local/share/cmake-3.22/Modules/CMakeCXXInformation.cmake"
		},
		{
			"isCMake" : true,
			"isExternal" : true,
			"path" : "/usr/local/share/cmake-3.22/Modules/CMakeLanguageInformation.cmake"
		},
		{
			"isCMake" : true,
			"isExternal" : true,
			"path" : "/usr/local/share/cmake-3.22/Modules/Compiler/GNU-CXX.cmake"
		},
		{
			"isCMake" : true,
			"isExternal" : true,
			"path" : "/usr/local/share/cmake-3.22/Modules/Compiler/GNU.cmake"
		},
		{
			"isCMake" : true,
			"isExternal" : true,
			"path" : "/usr/local/share/cmake-3.22/Modules/Compiler/CMakeCommonCompilerMacros.cmake"
		},
		{
			"isCMake" : true,
			"isExternal" : true,
			"path" : "/usr/local/share/cmake-3.22/Modules/Platform/Linux-GNU-CXX.cmake"
		},
		{
			"isCMake" : true,
			"isExternal" : true,
			"path" : "/usr/local/share/cmake-3.22/Modules/Platform/Linux-GNU.cmake"
		},
		{
			"isCMake" : true,
			"isExternal" : true,
			"path" : "/usr/local/share/cmake-3.22/Modules/CMakeCommonLanguageInclude.cmake"
		},
		{
			"isCMake" : true,
			"isExternal" : true,
			"path" : "/usr/local/share/cmake-3.22/Modules/FindProtobuf.cmake"
		},
		{
			"isCMake" : true,
			"isExternal" : true,
			"path" : "/usr/local/share/cmake-3.22/Modules/SelectLibraryConfigurations.cmake"
		},
		{
			"isCMake" : true,
			"isExternal" : true,
			"path" : "/usr/local/share/cmake-3.22/Modules/FindThreads.cmake"
		},
		{
			"isCMake" : true,
			"isExternal" : true,
			"path" : "/usr/local/share/cmake-3.22/Modules/CheckLibraryExists.cmake"
		},
		{
			"isCMake" : true,
			"isExternal" : true,
			"path" : "/usr/local/share/cmake-3.22/Modules/CheckIncludeFileCXX.cmake"
		},
		{
			"isCMake" : true,
			"isExternal" : true,
			"path" : "/usr/local/share/cmake-3.22/Modules/CheckCXXSourceCompiles.cmake"
		},
		{
			"isCMake" : true,
			"isExternal" : true,
			"path" : "/usr/local/share/cmake-3.22/Modules/Internal/CheckSourceCompiles.cmake"
		},
		{
			"isCMake" : true,
			"isExternal" : true,
			"path" : "/usr/local/share/cmake-3.22/Modules/FindPackageHandleStandardArgs.cmake"
		},
		{
			"isCMake" : true,
			"isExternal" : true,
			"path" : "/usr/local/share/cmake-3.22/Modules/FindPackageMessage.cmake"
		},
		{
			"isCMake" : true,
			"isExternal" : true,
			"path" : "/usr/local/share/cmake-3.22/Modules/FindPackageHandleStandardArgs.cmake"
		},
		{
			"isCMake" : true,
			"isExternal" : true,
			"path" : "/usr/local/share/cmake-3.22/Modules/FindPackageMessage.cmake"
		},
		{
			"isCMake" : true,
			"isExternal" : true,
			"path" : "/usr/local/share/cmake-3.22/Modules/FindThreads.cmake"
		},
		{
			"isCMake" : true,
			"isExternal" : true,
			"path" : "/usr/local/share/cmake-3.22/Modules/CheckLibraryExists.cmake"
		},
		{
			"isCMake" : true,
			"isExternal" : true,
			"path" : "/usr/local/share/cmake-3.22/Modules/CheckIncludeFileCXX.cmake"
		},
		{
			"isCMake" : true,
			"isExternal" : true,
			"path" : "/usr/local/share/cmake-3.22/Modules/CheckCXXSourceCompiles.cmake"
		},
		{
			"isCMake" : true,
			"isExternal" : true,
			"path" : "/usr/local/share/cmake-3.22/Modules/FindPackageHandleStandardArgs.cmake"
		},
		{
			"isCMake" : true,
			"isExternal" : true,
			"path" : "/usr/local/share/cmake-3.22/Modules/FindPackageMessage.cmake"
		}
	],
	"kind" : "cmakeFiles",
	"paths" : 
	{
		"build" : "/home/user/YPrC++/TransportCatalogue3/build-debug",
		"source" : "/home/user/YPrC++/TransportCatalogue3/transport_catalogue"
	},
	"version" : 
	{
		"major" : 1,
		"minor" : 0
	}
}
